anti_profanity/__init__.py
anti_profanity/cli.py
anti_profanity/main.py
anti_profanity/data/__init__.py
anti_profanity/data/bengali_en.py
anti_profanity/data/english_en.py
anti_profanity/data/hindi_en.py
anti_profanity-0.2.6.dist-info/licenses/LICENSE
anti_profanity-0.2.6.dist-info/METADATA
anti_profanity-0.2.6.dist-info/WHEEL
anti_profanity-0.2.6.dist-info/top_level.txt
anti_profanity-0.2.6.dist-info/RECORD
