Metadata-Version: 2.4
Name: anti-profanity
Version: 0.2.6
Summary: A multilingual profanity filter supporting English, Hindi, and Bengali
Home-page: https://github.com/MeeRazi/anti-profanity
Author: MeeRazi
Classifier: Development Status :: 4 - Beta
Classifier: Intended Audience :: Developers
Classifier: License :: OSI Approved :: MIT License
Classifier: Operating System :: OS Independent
Classifier: Programming Language :: Python :: 3
Classifier: Topic :: Text Processing :: Filters
Classifier: Natural Language :: English
Requires-Python: >=3.6
License-File: LICENSE
Dynamic: author
Dynamic: classifier
Dynamic: description
Dynamic: description-content-type
Dynamic: home-page
Dynamic: license-file
Dynamic: requires-python
Dynamic: summary
